mcp_server_rag/__init__.py
mcp_server_rag/__main__.py
mcp_server_rag/server.py
mcp_server_rag-0.2.0.dist-info/METADATA
mcp_server_rag-0.2.0.dist-info/WHEEL
mcp_server_rag-0.2.0.dist-info/entry_points.txt
mcp_server_rag-0.2.0.dist-info/top_level.txt
mcp_server_rag-0.2.0.dist-info/RECORD
