Metadata-Version: 2.4
Name: mcp-server-rag
Version: 0.2.0
Summary: MCP RAG server
Author-email: Aditya Mishra <adi.mishra989@gmail.com>
License-Expression: MIT
Classifier: Development Status :: 3 - Alpha
Classifier: Intended Audience :: Developers
Classifier: Programming Language :: Python :: 3
Classifier: Programming Language :: Python :: 3.8
Classifier: Programming Language :: Python :: 3.9
Classifier: Programming Language :: Python :: 3.10
Classifier: Programming Language :: Python :: 3.11
Requires-Python: >=3.10
Requires-Dist: click>=8.1.7
Requires-Dist: mcp>=1.0.0
Requires-Dist: chromadb==0.6.3
Requires-Dist: sentence-transformers==3.3.1
